stepwise/__init__.py
stepwise/__main__.py
stepwise/config.py
stepwise/errors.py
stepwise/library.py
stepwise/printer.py
stepwise/protocol.py
stepwise/quantity.py
stepwise/testing.py
stepwise/utils.py
stepwise/builtins/conditions.py
stepwise/builtins/echo.py
stepwise/builtins/reaction.py
stepwise/builtins/step.py
stepwise/builtins/future/reaction.py
stepwise/cli/__init__.py
stepwise/cli/edit.py
stepwise/cli/go.py
stepwise/cli/ls.py
stepwise/cli/main.py
stepwise/cli/metric.py
stepwise/cli/note.py
stepwise/cli/sub.py
stepwise/cli/which.py
stepwise/cli/stash/__init__.py
stepwise/cli/stash/main.py
stepwise/cli/stash/model.py
stepwise/cli/stash/pickler.py
stepwise/format/__init__.py
stepwise/format/format.py
stepwise/format/lists.py
stepwise/format/misc.py
stepwise/format/table.py
stepwise/reaction/__init__.py
stepwise/reaction/deprecated.py
stepwise/reaction/mix.py
stepwise/reaction/reaction.py
stepwise/reaction/reactions.py
stepwise-0.40.0.dist-info/entry_points.txt
stepwise-0.40.0.dist-info/LICENSE.txt
stepwise-0.40.0.dist-info/WHEEL
stepwise-0.40.0.dist-info/METADATA
stepwise-0.40.0.dist-info/RECORD
