Metadata-Version: 2.1
Name: stepwise
Version: 0.40.0
Summary: Wetlab protocols that follow the Unix philosophy.
Home-page: https://github.com/kalekundert/stepwise
Author: Kale Kundert
Author-email: kale@thekunderts.net
Requires-Python: ~=3.8
Classifier: Programming Language :: Python :: 3
Classifier: License :: OSI Approved :: GNU General Public License v3 (GPLv3)
Requires-Dist: byoc
Requires-Dist: arrow
Requires-Dist: autoprop
Requires-Dist: docopt
Requires-Dist: entrypoints
Requires-Dist: inform
Requires-Dist: more_itertools
Requires-Dist: reprfunc
Requires-Dist: sqlalchemy
Requires-Dist: voluptuous
Requires-Dist: pandas>=1.2
Requires-Dist: networkx
Requires-Dist: sphinx ; extra == "docs"
Requires-Dist: sphinx_rtd_theme ; extra == "docs"
Requires-Dist: autoclasstoc ; extra == "docs"
Requires-Dist: pytest ; extra == "tests"
Requires-Dist: pytest-cov ; extra == "tests"
Requires-Dist: pytest-unordered ; extra == "tests"
Requires-Dist: pytest_tmp_files ; extra == "tests"
Requires-Dist: coveralls ; extra == "tests"
Requires-Dist: parametrize_from_file ; extra == "tests"
Requires-Dist: openpyxl ; extra == "tests"
Requires-Dist: rtoml ; extra == "tests"
Requires-Dist: re_assert ; extra == "tests"
Project-URL: Bug Tracker, https://github.com/kalekundert/stepwise/issues
Project-URL: Continuous Integration, https://github.com/kalekundert/stepwise/actions
Project-URL: Documentation, https://stepwise.readthedocs.io/en/latest/
Project-URL: Test Coverage, https://coveralls.io/github/kalekundert/stepwise
Project-URL: Version Control, https://github.com/kalekundert/stepwise
Provides-Extra: docs
Provides-Extra: tests
